<?xml version="1.0" encoding="utf-8"?><Map tileSetPath="newTile.png" MapSizeX="10" MapSizeY="10" tileWidth="32" tileHeight="32"><Tile Collision="1" CompanionID="0" NextLevel="0" PrevLevel="0" MainLevel="0" SideLevel="0" Boulder="0" chestID="0" QTEvent="0" waypointID="0" enemyID="0" playerSpawn="0" startSlidingTile="0" endSlidingTile="0" checkPoint="0" trapID="0" sourceX="8" sourceY="15" xIndex="0" yIndex="0" /><Tile Collision="1" CompanionID="0" NextLevel="0" PrevLevel="0" MainLevel="0" SideLevel="0" Boulder="0" chestID="0" QTEvent="0" waypointID="0" enemyID="0" playerSpawn="0" startSlidingTile="0" endSlidingTile="0" checkPoint="0" trapID="0" sourceX="8" sourceY="15" xIndex="0" yIndex="1" /><Tile Collision="1" CompanionID="0" NextLevel="0" PrevLevel="0" MainLevel="0" SideLevel="0" Boulder="0" chestID="0" QTEvent="0" waypointID="0" enemyID="0" playerSpawn="0" startSlidingTile="0" endSlidingTile="0" checkPoint="0" trapID="0" sourceX="8" sourceY="15" xIndex="0" yIndex="2" /><Tile Collision="1" CompanionID="0" NextLevel="0" PrevLevel="0" MainLevel="0" SideLevel="0" Boulder="0" chestID="0" QTEvent="0" waypointID="0" enemyID="0" playerSpawn="0" startSlidingTile="0" endSlidingTile="0" checkPoint="0" trapID="0" sourceX="8" sourceY="15" xIndex="0" yIndex="3" /><Tile Collision="1" CompanionID="0" NextLevel="0" PrevLevel="0" MainLevel="0" SideLevel="0" Boulder="0" chestID="0" QTEvent="0" waypointID="0" enemyID="0" playerSpawn="0" startSlidingTile="0" endSlidingTile="0" checkPoint="0" trapID="0" sourceX="8" sourceY="15" xIndex="0" yIndex="4" /><Tile Collision="1" CompanionID="0" NextLevel="0" PrevLevel="0" MainLevel="0" SideLevel="0" Boulder="0" chestID="0" QTEvent="0" waypointID="0" enemyID="0" playerSpawn="0" startSlidingTile="0" endSlidingTile="0" checkPoint="0" trapID="0" sourceX="8" sourceY="15" xIndex="0" yIndex="5" /><Tile Collision="1" CompanionID="0" NextLevel="0" PrevLevel="0" MainLevel="0" SideLevel="0" Boulder="0" chestID="0" QTEvent="0" waypointID="0" enemyID="0" playerSpawn="0" startSlidingTile="0" endSlidingTile="0" checkPoint="0" trapID="0" sourceX="8" sourceY="15" xIndex="0" yIndex="6" /><Tile Collision="1" CompanionID="0" NextLevel="0" PrevLevel="0" MainLevel="0" SideLevel="0" Boulder="0" chestID="0" QTEvent="0" waypointID="0" enemyID="0" playerSpawn="0" startSlidingTile="0" endSlidingTile="0" checkPoint="0" trapID="0" sourceX="8" sourceY="15" xIndex="0" yIndex="7" /><Tile Collision="1" CompanionID="0" NextLevel="0" PrevLevel="0" MainLevel="0" SideLevel="0" Boulder="0" chestID="0" QTEvent="0" waypointID="0" enemyID="0" playerSpawn="0" startSlidingTile="0" endSlidingTile="0" checkPoint="0" trapID="0" sourceX="8" sourceY="15" xIndex="0" yIndex="8" /><Tile Collision="1" CompanionID="0" NextLevel="0" PrevLevel="0" MainLevel="0" SideLevel="0" Boulder="0" chestID="0" QTEvent="0" waypointID="0" enemyID="0" playerSpawn="0" startSlidingTile="0" endSlidingTile="0" checkPoint="0" trapID="0" sourceX="8" sourceY="15" xIndex="0" yIndex="9" /><Tile Collision="1" CompanionID="0" NextLevel="0" PrevLevel="0" MainLevel="0" SideLevel="0" Boulder="0" chestID="0" QTEvent="0" waypointID="0" enemyID="0" playerSpawn="0" startSlidingTile="0" endSlidingTile="0" checkPoint="0" trapID="0" sourceX="8" sourceY="15" xIndex="1" yIndex="0" /><Tile Collision="0" CompanionID="0" NextLevel="0" PrevLevel="0" MainLevel="0" SideLevel="0" Boulder="0" chestID="0" QTEvent="0" waypointID="0" enemyID="0" playerSpawn="0" startSlidingTile="0" endSlidingTile="0" checkPoint="0" trapID="0" sourceX="17" sourceY="2" xIndex="1" yIndex="1" /><Tile Collision="0" CompanionID="0" NextLevel="0" PrevLevel="0" MainLevel="0" SideLevel="0" Boulder="0" chestID="0" QTEvent="0" waypointID="0" enemyID="0" playerSpawn="0" startSlidingTile="0" endSlidingTile="0" checkPoint="0" trapID="0" sourceX="17" sourceY="2" xIndex="1" yIndex="2" /><Tile Collision="0" CompanionID="0" NextLevel="0" PrevLevel="0" MainLevel="0" SideLevel="0" Boulder="0" chestID="0" QTEvent="0" waypointID="0" enemyID="0" playerSpawn="0" startSlidingTile="0" endSlidingTile="0" checkPoint="0" trapID="0" sourceX="17" sourceY="2" xIndex="1" yIndex="3" /><Tile Collision="0" CompanionID="0" NextLevel="0" PrevLevel="0" MainLevel="0" SideLevel="0" Boulder="0" chestID="0" QTEvent="0" waypointID="0" enemyID="0" playerSpawn="0" startSlidingTile="0" endSlidingTile="0" checkPoint="0" trapID="0" sourceX="17" sourceY="2" xIndex="1" yIndex="4" /><Tile Collision="0" CompanionID="0" NextLevel="0" PrevLevel="0" MainLevel="0" SideLevel="0" Boulder="0" chestID="0" QTEvent="0" waypointID="0" enemyID="0" playerSpawn="0" startSlidingTile="0" endSlidingTile="0" checkPoint="0" trapID="0" sourceX="17" sourceY="2" xIndex="1" yIndex="5" /><Tile Collision="0" CompanionID="0" NextLevel="0" PrevLevel="0" MainLevel="0" SideLevel="0" Boulder="0" chestID="0" QTEvent="0" waypointID="0" enemyID="0" playerSpawn="0" startSlidingTile="0" endSlidingTile="0" checkPoint="0" trapID="0" sourceX="17" sourceY="2" xIndex="1" yIndex="6" /><Tile Collision="0" CompanionID="0" NextLevel="0" PrevLevel="0" MainLevel="0" SideLevel="0" Boulder="0" chestID="0" QTEvent="0" waypointID="0" enemyID="0" playerSpawn="0" startSlidingTile="0" endSlidingTile="0" checkPoint="0" trapID="0" sourceX="17" sourceY="2" xIndex="1" yIndex="7" /><Tile Collision="0" CompanionID="0" NextLevel="0" PrevLevel="0" MainLevel="0" SideLevel="0" Boulder="0" chestID="0" QTEvent="0" waypointID="0" enemyID="0" playerSpawn="0" startSlidingTile="0" endSlidingTile="0" checkPoint="0" trapID="0" sourceX="17" sourceY="2" xIndex="1" yIndex="8" /><Tile Collision="1" CompanionID="0" NextLevel="0" PrevLevel="0" MainLevel="0" SideLevel="0" Boulder="0" chestID="0" QTEvent="0" waypointID="0" enemyID="0" playerSpawn="0" startSlidingTile="0" endSlidingTile="0" checkPoint="0" trapID="0" sourceX="8" sourceY="15" xIndex="1" yIndex="9" /><Tile Collision="1" CompanionID="0" NextLevel="0" PrevLevel="0" MainLevel="0" SideLevel="0" Boulder="0" chestID="0" QTEvent="0" waypointID="0" enemyID="0" playerSpawn="0" startSlidingTile="0" endSlidingTile="0" checkPoint="0" trapID="0" sourceX="8" sourceY="15" xIndex="2" yIndex="0" /><Tile Collision="0" CompanionID="0" NextLevel="0" PrevLevel="0" MainLevel="0" SideLevel="0" Boulder="0" chestID="0" QTEvent="0" waypointID="0" enemyID="0" playerSpawn="0" startSlidingTile="0" endSlidingTile="0" checkPoint="0" trapID="0" sourceX="17" sourceY="2" xIndex="2" yIndex="1" /><Tile Collision="0" CompanionID="0" NextLevel="0" PrevLevel="0" MainLevel="0" SideLevel="0" Boulder="0" chestID="0" QTEvent="0" waypointID="0" enemyID="0" playerSpawn="0" startSlidingTile="0" endSlidingTile="0" checkPoint="0" trapID="0" sourceX="17" sourceY="2" xIndex="2" yIndex="2" /><Tile Collision="0" CompanionID="0" NextLevel="0" PrevLevel="0" MainLevel="0" SideLevel="0" Boulder="0" chestID="0" QTEvent="0" waypointID="2" enemyID="0" playerSpawn="0" startSlidingTile="0" endSlidingTile="0" checkPoint="0" trapID="0" sourceX="17" sourceY="2" xIndex="2" yIndex="3" /><Tile Collision="0" CompanionID="0" NextLevel="0" PrevLevel="0" MainLevel="0" SideLevel="0" Boulder="0" chestID="0" QTEvent="0" waypointID="0" enemyID="0" playerSpawn="0" startSlidingTile="0" endSlidingTile="0" checkPoint="0" trapID="0" sourceX="17" sourceY="2" xIndex="2" yIndex="4" /><Tile Collision="0" CompanionID="0" NextLevel="0" PrevLevel="0" MainLevel="0" SideLevel="0" Boulder="0" chestID="0" QTEvent="0" waypointID="0" enemyID="0" playerSpawn="0" startSlidingTile="0" endSlidingTile="0" checkPoint="0" trapID="0" sourceX="17" sourceY="2" xIndex="2" yIndex="5" /><Tile Collision="0" CompanionID="0" NextLevel="0" PrevLevel="0" MainLevel="0" SideLevel="0" Boulder="0" chestID="0" QTEvent="0" waypointID="0" enemyID="0" playerSpawn="0" startSlidingTile="0" endSlidingTile="0" checkPoint="0" trapID="0" sourceX="17" sourceY="2" xIndex="2" yIndex="6" /><Tile Collision="0" CompanionID="0" NextLevel="0" PrevLevel="0" MainLevel="0" SideLevel="0" Boulder="0" chestID="0" QTEvent="0" waypointID="0" enemyID="0" playerSpawn="0" startSlidingTile="0" endSlidingTile="0" checkPoint="0" trapID="0" sourceX="17" sourceY="2" xIndex="2" yIndex="7" /><Tile Collision="0" CompanionID="0" NextLevel="0" PrevLevel="0" MainLevel="0" SideLevel="0" Boulder="0" chestID="0" QTEvent="0" waypointID="0" enemyID="0" playerSpawn="0" startSlidingTile="0" endSlidingTile="0" checkPoint="0" trapID="0" sourceX="17" sourceY="2" xIndex="2" yIndex="8" /><Tile Collision="1" CompanionID="0" NextLevel="0" PrevLevel="0" MainLevel="0" SideLevel="0" Boulder="0" chestID="0" QTEvent="0" waypointID="0" enemyID="0" playerSpawn="0" startSlidingTile="0" endSlidingTile="0" checkPoint="0" trapID="0" sourceX="2" sourceY="15" xIndex="2" yIndex="9" /><Tile Collision="1" CompanionID="0" NextLevel="0" PrevLevel="0" MainLevel="0" SideLevel="0" Boulder="0" chestID="0" QTEvent="0" waypointID="0" enemyID="0" playerSpawn="0" startSlidingTile="0" endSlidingTile="0" checkPoint="0" trapID="0" sourceX="2" sourceY="15" xIndex="3" yIndex="0" /><Tile Collision="0" CompanionID="0" NextLevel="0" PrevLevel="0" MainLevel="0" SideLevel="0" Boulder="0" chestID="0" QTEvent="0" waypointID="0" enemyID="0" playerSpawn="0" startSlidingTile="0" endSlidingTile="0" checkPoint="0" trapID="0" sourceX="17" sourceY="2" xIndex="3" yIndex="1" /><Tile Collision="0" CompanionID="0" NextLevel="0" PrevLevel="0" MainLevel="0" SideLevel="0" Boulder="0" chestID="0" QTEvent="0" waypointID="0" enemyID="0" playerSpawn="0" startSlidingTile="0" endSlidingTile="0" checkPoint="0" trapID="0" sourceX="17" sourceY="2" xIndex="3" yIndex="2" /><Tile Collision="0" CompanionID="0" NextLevel="0" PrevLevel="0" MainLevel="0" SideLevel="0" Boulder="0" chestID="0" QTEvent="0" waypointID="0" enemyID="0" playerSpawn="0" startSlidingTile="0" endSlidingTile="0" checkPoint="0" trapID="0" sourceX="17" sourceY="2" xIndex="3" yIndex="3" /><Tile Collision="0" CompanionID="0" NextLevel="0" PrevLevel="0" MainLevel="0" SideLevel="0" Boulder="0" chestID="0" QTEvent="0" waypointID="0" enemyID="0" playerSpawn="0" startSlidingTile="0" endSlidingTile="0" checkPoint="0" trapID="0" sourceX="17" sourceY="2" xIndex="3" yIndex="4" /><Tile Collision="0" CompanionID="0" NextLevel="0" PrevLevel="0" MainLevel="0" SideLevel="0" Boulder="0" chestID="0" QTEvent="0" waypointID="0" enemyID="0" playerSpawn="0" startSlidingTile="0" endSlidingTile="0" checkPoint="0" trapID="0" sourceX="17" sourceY="2" xIndex="3" yIndex="5" /><Tile Collision="0" CompanionID="0" NextLevel="0" PrevLevel="0" MainLevel="0" SideLevel="0" Boulder="0" chestID="0" QTEvent="0" waypointID="0" enemyID="1" playerSpawn="0" startSlidingTile="0" endSlidingTile="0" checkPoint="0" trapID="0" sourceX="17" sourceY="2" xIndex="3" yIndex="6" /><Tile Collision="0" CompanionID="0" NextLevel="0" PrevLevel="0" MainLevel="0" SideLevel="0" Boulder="0" chestID="0" QTEvent="0" waypointID="0" enemyID="0" playerSpawn="0" startSlidingTile="0" endSlidingTile="0" checkPoint="0" trapID="0" sourceX="17" sourceY="2" xIndex="3" yIndex="7" /><Tile Collision="0" CompanionID="0" NextLevel="0" PrevLevel="0" MainLevel="0" SideLevel="0" Boulder="0" chestID="0" QTEvent="0" waypointID="0" enemyID="0" playerSpawn="0" startSlidingTile="0" endSlidingTile="0" checkPoint="0" trapID="0" sourceX="17" sourceY="2" xIndex="3" yIndex="8" /><Tile Collision="1" CompanionID="0" NextLevel="0" PrevLevel="0" MainLevel="0" SideLevel="0" Boulder="0" chestID="0" QTEvent="0" waypointID="0" enemyID="0" playerSpawn="0" startSlidingTile="0" endSlidingTile="0" checkPoint="0" trapID="0" sourceX="8" sourceY="15" xIndex="3" yIndex="9" /><Tile Collision="1" CompanionID="0" NextLevel="0" PrevLevel="0" MainLevel="0" SideLevel="0" Boulder="0" chestID="0" QTEvent="0" waypointID="0" enemyID="0" playerSpawn="0" startSlidingTile="0" endSlidingTile="0" checkPoint="0" trapID="0" sourceX="2" sourceY="15" xIndex="4" yIndex="0" /><Tile Collision="0" CompanionID="0" NextLevel="0" PrevLevel="0" MainLevel="0" SideLevel="0" Boulder="0" chestID="0" QTEvent="0" waypointID="0" enemyID="0" playerSpawn="0" startSlidingTile="0" endSlidingTile="0" checkPoint="0" trapID="0" sourceX="17" sourceY="2" xIndex="4" yIndex="1" /><Tile Collision="0" CompanionID="0" NextLevel="0" PrevLevel="0" MainLevel="0" SideLevel="0" Boulder="0" chestID="0" QTEvent="0" waypointID="0" enemyID="0" playerSpawn="0" startSlidingTile="0" endSlidingTile="0" checkPoint="0" trapID="0" sourceX="17" sourceY="2" xIndex="4" yIndex="2" /><Tile Collision="0" CompanionID="0" NextLevel="0" PrevLevel="0" MainLevel="0" SideLevel="0" Boulder="0" chestID="0" QTEvent="0" waypointID="0" enemyID="0" playerSpawn="0" startSlidingTile="0" endSlidingTile="0" checkPoint="0" trapID="0" sourceX="17" sourceY="2" xIndex="4" yIndex="3" /><Tile Collision="0" CompanionID="0" NextLevel="0" PrevLevel="0" MainLevel="0" SideLevel="0" Boulder="0" chestID="0" QTEvent="0" waypointID="0" enemyID="0" playerSpawn="0" startSlidingTile="0" endSlidingTile="0" checkPoint="0" trapID="0" sourceX="17" sourceY="2" xIndex="4" yIndex="4" /><Tile Collision="0" CompanionID="0" NextLevel="0" PrevLevel="0" MainLevel="0" SideLevel="0" Boulder="0" chestID="0" QTEvent="0" waypointID="0" enemyID="0" playerSpawn="0" startSlidingTile="0" endSlidingTile="0" checkPoint="0" trapID="0" sourceX="17" sourceY="2" xIndex="4" yIndex="5" /><Tile Collision="0" CompanionID="0" NextLevel="0" PrevLevel="0" MainLevel="0" SideLevel="0" Boulder="0" chestID="0" QTEvent="0" waypointID="1" enemyID="0" playerSpawn="0" startSlidingTile="0" endSlidingTile="0" checkPoint="0" trapID="0" sourceX="17" sourceY="2" xIndex="4" yIndex="6" /><Tile Collision="0" CompanionID="0" NextLevel="0" PrevLevel="0" MainLevel="0" SideLevel="0" Boulder="0" chestID="0" QTEvent="0" waypointID="0" enemyID="0" playerSpawn="0" startSlidingTile="0" endSlidingTile="0" checkPoint="0" trapID="0" sourceX="17" sourceY="2" xIndex="4" yIndex="7" /><Tile Collision="0" CompanionID="0" NextLevel="0" PrevLevel="0" MainLevel="0" SideLevel="0" Boulder="0" chestID="0" QTEvent="0" waypointID="0" enemyID="0" playerSpawn="1" startSlidingTile="0" endSlidingTile="0" checkPoint="0" trapID="0" sourceX="17" sourceY="2" xIndex="4" yIndex="8" /><Tile Collision="0" CompanionID="0" NextLevel="0" PrevLevel="0" MainLevel="1" SideLevel="0" Boulder="0" chestID="0" QTEvent="0" waypointID="0" enemyID="0" playerSpawn="0" startSlidingTile="0" endSlidingTile="0" checkPoint="0" trapID="0" sourceX="15" sourceY="20" xIndex="4" yIndex="9" /><Tile Collision="1" CompanionID="0" NextLevel="0" PrevLevel="0" MainLevel="0" SideLevel="0" Boulder="0" chestID="0" QTEvent="0" waypointID="0" enemyID="0" playerSpawn="0" startSlidingTile="0" endSlidingTile="0" checkPoint="0" trapID="0" sourceX="2" sourceY="15" xIndex="5" yIndex="0" /><Tile Collision="0" CompanionID="0" NextLevel="0" PrevLevel="0" MainLevel="0" SideLevel="0" Boulder="0" chestID="2" QTEvent="0" waypointID="0" enemyID="0" playerSpawn="0" startSlidingTile="0" endSlidingTile="0" checkPoint="0" trapID="0" sourceX="17" sourceY="2" xIndex="5" yIndex="1" /><Tile Collision="0" CompanionID="0" NextLevel="0" PrevLevel="0" MainLevel="0" SideLevel="0" Boulder="0" chestID="0" QTEvent="0" waypointID="0" enemyID="1" playerSpawn="0" startSlidingTile="0" endSlidingTile="0" checkPoint="0" trapID="0" sourceX="17" sourceY="2" xIndex="5" yIndex="2" /><Tile Collision="0" CompanionID="0" NextLevel="0" PrevLevel="0" MainLevel="0" SideLevel="0" Boulder="0" chestID="0" QTEvent="0" waypointID="0" enemyID="0" playerSpawn="0" startSlidingTile="0" endSlidingTile="0" checkPoint="0" trapID="0" sourceX="17" sourceY="2" xIndex="5" yIndex="3" /><Tile Collision="0" CompanionID="0" NextLevel="0" PrevLevel="0" MainLevel="0" SideLevel="0" Boulder="0" chestID="0" QTEvent="0" waypointID="0" enemyID="0" playerSpawn="0" startSlidingTile="0" endSlidingTile="0" checkPoint="0" trapID="0" sourceX="17" sourceY="2" xIndex="5" yIndex="4" /><Tile Collision="0" CompanionID="0" NextLevel="0" PrevLevel="0" MainLevel="0" SideLevel="0" Boulder="0" chestID="0" QTEvent="0" waypointID="0" enemyID="0" playerSpawn="0" startSlidingTile="0" endSlidingTile="0" checkPoint="0" trapID="0" sourceX="17" sourceY="2" xIndex="5" yIndex="5" /><Tile Collision="0" CompanionID="0" NextLevel="0" PrevLevel="0" MainLevel="0" SideLevel="0" Boulder="0" chestID="0" QTEvent="0" waypointID="0" enemyID="0" playerSpawn="0" startSlidingTile="0" endSlidingTile="0" checkPoint="0" trapID="0" sourceX="17" sourceY="2" xIndex="5" yIndex="6" /><Tile Collision="0" CompanionID="0" NextLevel="0" PrevLevel="0" MainLevel="0" SideLevel="0" Boulder="0" chestID="0" QTEvent="0" waypointID="0" enemyID="0" playerSpawn="0" startSlidingTile="0" endSlidingTile="0" checkPoint="0" trapID="0" sourceX="17" sourceY="2" xIndex="5" yIndex="7" /><Tile Collision="0" CompanionID="0" NextLevel="0" PrevLevel="0" MainLevel="0" SideLevel="0" Boulder="0" chestID="0" QTEvent="0" waypointID="0" enemyID="0" playerSpawn="0" startSlidingTile="0" endSlidingTile="0" checkPoint="0" trapID="0" sourceX="17" sourceY="2" xIndex="5" yIndex="8" /><Tile Collision="1" CompanionID="0" NextLevel="0" PrevLevel="0" MainLevel="0" SideLevel="0" Boulder="0" chestID="0" QTEvent="0" waypointID="0" enemyID="0" playerSpawn="0" startSlidingTile="0" endSlidingTile="0" checkPoint="0" trapID="0" sourceX="8" sourceY="15" xIndex="5" yIndex="9" /><Tile Collision="1" CompanionID="0" NextLevel="0" PrevLevel="0" MainLevel="0" SideLevel="0" Boulder="0" chestID="0" QTEvent="0" waypointID="0" enemyID="0" playerSpawn="0" startSlidingTile="0" endSlidingTile="0" checkPoint="0" trapID="0" sourceX="2" sourceY="15" xIndex="6" yIndex="0" /><Tile Collision="0" CompanionID="0" NextLevel="0" PrevLevel="0" MainLevel="0" SideLevel="0" Boulder="0" chestID="0" QTEvent="0" waypointID="0" enemyID="0" playerSpawn="0" startSlidingTile="0" endSlidingTile="0" checkPoint="0" trapID="0" sourceX="17" sourceY="2" xIndex="6" yIndex="1" /><Tile Collision="0" CompanionID="0" NextLevel="0" PrevLevel="0" MainLevel="0" SideLevel="0" Boulder="0" chestID="0" QTEvent="0" waypointID="3" enemyID="0" playerSpawn="0" startSlidingTile="0" endSlidingTile="0" checkPoint="0" trapID="0" sourceX="17" sourceY="2" xIndex="6" yIndex="2" /><Tile Collision="0" CompanionID="0" NextLevel="0" PrevLevel="0" MainLevel="0" SideLevel="0" Boulder="0" chestID="0" QTEvent="0" waypointID="0" enemyID="0" playerSpawn="0" startSlidingTile="0" endSlidingTile="0" checkPoint="0" trapID="0" sourceX="17" sourceY="2" xIndex="6" yIndex="3" /><Tile Collision="0" CompanionID="0" NextLevel="0" PrevLevel="0" MainLevel="0" SideLevel="0" Boulder="0" chestID="0" QTEvent="0" waypointID="0" enemyID="0" playerSpawn="0" startSlidingTile="0" endSlidingTile="0" checkPoint="0" trapID="0" sourceX="17" sourceY="2" xIndex="6" yIndex="4" /><Tile Collision="0" CompanionID="0" NextLevel="0" PrevLevel="0" MainLevel="0" SideLevel="0" Boulder="0" chestID="0" QTEvent="0" waypointID="0" enemyID="0" playerSpawn="0" startSlidingTile="0" endSlidingTile="0" checkPoint="0" trapID="0" sourceX="17" sourceY="2" xIndex="6" yIndex="5" /><Tile Collision="0" CompanionID="0" NextLevel="0" PrevLevel="0" MainLevel="0" SideLevel="0" Boulder="0" chestID="0" QTEvent="0" waypointID="0" enemyID="0" playerSpawn="0" startSlidingTile="0" endSlidingTile="0" checkPoint="0" trapID="0" sourceX="17" sourceY="2" xIndex="6" yIndex="6" /><Tile Collision="0" CompanionID="0" NextLevel="0" PrevLevel="0" MainLevel="0" SideLevel="0" Boulder="0" chestID="0" QTEvent="0" waypointID="0" enemyID="0" playerSpawn="0" startSlidingTile="0" endSlidingTile="0" checkPoint="0" trapID="0" sourceX="17" sourceY="2" xIndex="6" yIndex="7" /><Tile Collision="0" CompanionID="0" NextLevel="0" PrevLevel="0" MainLevel="0" SideLevel="0" Boulder="0" chestID="0" QTEvent="0" waypointID="0" enemyID="0" playerSpawn="0" startSlidingTile="0" endSlidingTile="0" checkPoint="0" trapID="0" sourceX="17" sourceY="2" xIndex="6" yIndex="8" /><Tile Collision="1" CompanionID="0" NextLevel="0" PrevLevel="0" MainLevel="0" SideLevel="0" Boulder="0" chestID="0" QTEvent="0" waypointID="0" enemyID="0" playerSpawn="0" startSlidingTile="0" endSlidingTile="0" checkPoint="0" trapID="0" sourceX="2" sourceY="15" xIndex="6" yIndex="9" /><Tile Collision="1" CompanionID="0" NextLevel="0" PrevLevel="0" MainLevel="0" SideLevel="0" Boulder="0" chestID="0" QTEvent="0" waypointID="0" enemyID="0" playerSpawn="0" startSlidingTile="0" endSlidingTile="0" checkPoint="0" trapID="0" sourceX="8" sourceY="15" xIndex="7" yIndex="0" /><Tile Collision="0" CompanionID="0" NextLevel="0" PrevLevel="0" MainLevel="0" SideLevel="0" Boulder="0" chestID="0" QTEvent="0" waypointID="0" enemyID="0" playerSpawn="0" startSlidingTile="0" endSlidingTile="0" checkPoint="0" trapID="0" sourceX="17" sourceY="2" xIndex="7" yIndex="1" /><Tile Collision="0" CompanionID="0" NextLevel="0" PrevLevel="0" MainLevel="0" SideLevel="0" Boulder="0" chestID="0" QTEvent="0" waypointID="0" enemyID="0" playerSpawn="0" startSlidingTile="0" endSlidingTile="0" checkPoint="0" trapID="0" sourceX="17" sourceY="2" xIndex="7" yIndex="2" /><Tile Collision="0" CompanionID="0" NextLevel="0" PrevLevel="0" MainLevel="0" SideLevel="0" Boulder="0" chestID="0" QTEvent="0" waypointID="0" enemyID="0" playerSpawn="0" startSlidingTile="0" endSlidingTile="0" checkPoint="0" trapID="0" sourceX="17" sourceY="2" xIndex="7" yIndex="3" /><Tile Collision="0" CompanionID="0" NextLevel="0" PrevLevel="0" MainLevel="0" SideLevel="0" Boulder="0" chestID="0" QTEvent="0" waypointID="0" enemyID="0" playerSpawn="0" startSlidingTile="0" endSlidingTile="0" checkPoint="0" trapID="0" sourceX="17" sourceY="2" xIndex="7" yIndex="4" /><Tile Collision="0" CompanionID="0" NextLevel="0" PrevLevel="0" MainLevel="0" SideLevel="0" Boulder="0" chestID="0" QTEvent="0" waypointID="0" enemyID="0" playerSpawn="0" startSlidingTile="0" endSlidingTile="0" checkPoint="0" trapID="0" sourceX="17" sourceY="2" xIndex="7" yIndex="5" /><Tile Collision="0" CompanionID="0" NextLevel="0" PrevLevel="0" MainLevel="0" SideLevel="0" Boulder="0" chestID="0" QTEvent="0" waypointID="0" enemyID="0" playerSpawn="0" startSlidingTile="0" endSlidingTile="0" checkPoint="0" trapID="0" sourceX="17" sourceY="2" xIndex="7" yIndex="6" /><Tile Collision="0" CompanionID="0" NextLevel="0" PrevLevel="0" MainLevel="0" SideLevel="0" Boulder="0" chestID="0" QTEvent="0" waypointID="0" enemyID="0" playerSpawn="0" startSlidingTile="0" endSlidingTile="0" checkPoint="0" trapID="0" sourceX="17" sourceY="2" xIndex="7" yIndex="7" /><Tile Collision="0" CompanionID="0" NextLevel="0" PrevLevel="0" MainLevel="0" SideLevel="0" Boulder="0" chestID="0" QTEvent="0" waypointID="0" enemyID="0" playerSpawn="0" startSlidingTile="0" endSlidingTile="0" checkPoint="0" trapID="0" sourceX="17" sourceY="2" xIndex="7" yIndex="8" /><Tile Collision="1" CompanionID="0" NextLevel="0" PrevLevel="0" MainLevel="0" SideLevel="0" Boulder="0" chestID="0" QTEvent="0" waypointID="0" enemyID="0" playerSpawn="0" startSlidingTile="0" endSlidingTile="0" checkPoint="0" trapID="0" sourceX="2" sourceY="15" xIndex="7" yIndex="9" /><Tile Collision="1" CompanionID="0" NextLevel="0" PrevLevel="0" MainLevel="0" SideLevel="0" Boulder="0" chestID="0" QTEvent="0" waypointID="0" enemyID="0" playerSpawn="0" startSlidingTile="0" endSlidingTile="0" checkPoint="0" trapID="0" sourceX="8" sourceY="15" xIndex="8" yIndex="0" /><Tile Collision="0" CompanionID="0" NextLevel="0" PrevLevel="0" MainLevel="0" SideLevel="0" Boulder="0" chestID="0" QTEvent="0" waypointID="0" enemyID="0" playerSpawn="0" startSlidingTile="0" endSlidingTile="0" checkPoint="0" trapID="0" sourceX="17" sourceY="2" xIndex="8" yIndex="1" /><Tile Collision="0" CompanionID="0" NextLevel="0" PrevLevel="0" MainLevel="0" SideLevel="0" Boulder="0" chestID="0" QTEvent="0" waypointID="0" enemyID="0" playerSpawn="0" startSlidingTile="0" endSlidingTile="0" checkPoint="0" trapID="0" sourceX="17" sourceY="2" xIndex="8" yIndex="2" /><Tile Collision="0" CompanionID="0" NextLevel="0" PrevLevel="0" MainLevel="0" SideLevel="0" Boulder="0" chestID="0" QTEvent="0" waypointID="0" enemyID="0" playerSpawn="0" startSlidingTile="0" endSlidingTile="0" checkPoint="0" trapID="0" sourceX="17" sourceY="2" xIndex="8" yIndex="3" /><Tile Collision="0" CompanionID="0" NextLevel="0" PrevLevel="0" MainLevel="0" SideLevel="0" Boulder="0" chestID="0" QTEvent="0" waypointID="0" enemyID="0" playerSpawn="0" startSlidingTile="0" endSlidingTile="0" checkPoint="0" trapID="0" sourceX="17" sourceY="2" xIndex="8" yIndex="4" /><Tile Collision="0" CompanionID="0" NextLevel="0" PrevLevel="0" MainLevel="0" SideLevel="0" Boulder="0" chestID="0" QTEvent="0" waypointID="0" enemyID="0" playerSpawn="0" startSlidingTile="0" endSlidingTile="0" checkPoint="0" trapID="0" sourceX="17" sourceY="2" xIndex="8" yIndex="5" /><Tile Collision="0" CompanionID="0" NextLevel="0" PrevLevel="0" MainLevel="0" SideLevel="0" Boulder="0" chestID="0" QTEvent="0" waypointID="0" enemyID="0" playerSpawn="0" startSlidingTile="0" endSlidingTile="0" checkPoint="0" trapID="0" sourceX="17" sourceY="2" xIndex="8" yIndex="6" /><Tile Collision="0" CompanionID="0" NextLevel="0" PrevLevel="0" MainLevel="0" SideLevel="0" Boulder="0" chestID="0" QTEvent="0" waypointID="0" enemyID="0" playerSpawn="0" startSlidingTile="0" endSlidingTile="0" checkPoint="0" trapID="0" sourceX="17" sourceY="2" xIndex="8" yIndex="7" /><Tile Collision="0" CompanionID="0" NextLevel="0" PrevLevel="0" MainLevel="0" SideLevel="0" Boulder="0" chestID="0" QTEvent="0" waypointID="0" enemyID="0" playerSpawn="0" startSlidingTile="0" endSlidingTile="0" checkPoint="0" trapID="0" sourceX="17" sourceY="2" xIndex="8" yIndex="8" /><Tile Collision="1" CompanionID="0" NextLevel="0" PrevLevel="0" MainLevel="0" SideLevel="0" Boulder="0" chestID="0" QTEvent="0" waypointID="0" enemyID="0" playerSpawn="0" startSlidingTile="0" endSlidingTile="0" checkPoint="0" trapID="0" sourceX="8" sourceY="15" xIndex="8" yIndex="9" /><Tile Collision="1" CompanionID="0" NextLevel="0" PrevLevel="0" MainLevel="0" SideLevel="0" Boulder="0" chestID="0" QTEvent="0" waypointID="0" enemyID="0" playerSpawn="0" startSlidingTile="0" endSlidingTile="0" checkPoint="0" trapID="0" sourceX="8" sourceY="15" xIndex="9" yIndex="0" /><Tile Collision="1" CompanionID="0" NextLevel="0" PrevLevel="0" MainLevel="0" SideLevel="0" Boulder="0" chestID="0" QTEvent="0" waypointID="0" enemyID="0" playerSpawn="0" startSlidingTile="0" endSlidingTile="0" checkPoint="0" trapID="0" sourceX="8" sourceY="15" xIndex="9" yIndex="1" /><Tile Collision="1" CompanionID="0" NextLevel="0" PrevLevel="0" MainLevel="0" SideLevel="0" Boulder="0" chestID="0" QTEvent="0" waypointID="0" enemyID="0" playerSpawn="0" startSlidingTile="0" endSlidingTile="0" checkPoint="0" trapID="0" sourceX="8" sourceY="15" xIndex="9" yIndex="2" /><Tile Collision="1" CompanionID="0" NextLevel="0" PrevLevel="0" MainLevel="0" SideLevel="0" Boulder="0" chestID="0" QTEvent="0" waypointID="0" enemyID="0" playerSpawn="0" startSlidingTile="0" endSlidingTile="0" checkPoint="0" trapID="0" sourceX="8" sourceY="15" xIndex="9" yIndex="3" /><Tile Collision="1" CompanionID="0" NextLevel="0" PrevLevel="0" MainLevel="0" SideLevel="0" Boulder="0" chestID="0" QTEvent="0" waypointID="0" enemyID="0" playerSpawn="0" startSlidingTile="0" endSlidingTile="0" checkPoint="0" trapID="0" sourceX="8" sourceY="15" xIndex="9" yIndex="4" /><Tile Collision="1" CompanionID="0" NextLevel="0" PrevLevel="0" MainLevel="0" SideLevel="0" Boulder="0" chestID="0" QTEvent="0" waypointID="0" enemyID="0" playerSpawn="0" startSlidingTile="0" endSlidingTile="0" checkPoint="0" trapID="0" sourceX="8" sourceY="15" xIndex="9" yIndex="5" /><Tile Collision="1" CompanionID="0" NextLevel="0" PrevLevel="0" MainLevel="0" SideLevel="0" Boulder="0" chestID="0" QTEvent="0" waypointID="0" enemyID="0" playerSpawn="0" startSlidingTile="0" endSlidingTile="0" checkPoint="0" trapID="0" sourceX="8" sourceY="15" xIndex="9" yIndex="6" /><Tile Collision="1" CompanionID="0" NextLevel="0" PrevLevel="0" MainLevel="0" SideLevel="0" Boulder="0" chestID="0" QTEvent="0" waypointID="0" enemyID="0" playerSpawn="0" startSlidingTile="0" endSlidingTile="0" checkPoint="0" trapID="0" sourceX="8" sourceY="15" xIndex="9" yIndex="7" /><Tile Collision="1" CompanionID="0" NextLevel="0" PrevLevel="0" MainLevel="0" SideLevel="0" Boulder="0" chestID="0" QTEvent="0" waypointID="0" enemyID="0" playerSpawn="0" startSlidingTile="0" endSlidingTile="0" checkPoint="0" trapID="0" sourceX="8" sourceY="15" xIndex="9" yIndex="8" /><Tile Collision="1" CompanionID="0" NextLevel="0" PrevLevel="0" MainLevel="0" SideLevel="0" Boulder="0" chestID="0" QTEvent="0" waypointID="0" enemyID="0" playerSpawn="0" startSlidingTile="0" endSlidingTile="0" checkPoint="0" trapID="0" sourceX="8" sourceY="15" xIndex="9" yIndex="9" /></Map>